dotplotlib/__init__.py
dotplotlib/plots.py
dotplotlib-1.1.8.dist-info/LICENSE
dotplotlib-1.1.8.dist-info/METADATA
dotplotlib-1.1.8.dist-info/WHEEL
dotplotlib-1.1.8.dist-info/top_level.txt
dotplotlib-1.1.8.dist-info/RECORD
