Metadata-Version: 2.1
Name: dotplotlib
Version: 1.1.8
Summary: An extension library for creating strip plots or dot charts w/ matplotlib + seaboard
Home-page: https://github.com/jl33-ai/dotplotlib
Author: Justin Lee
Author-email: justinkhlee27@gmail.com
Classifier: Development Status :: 3 - Alpha
Classifier: Intended Audience :: Developers
Classifier: Programming Language :: Python :: 3
Classifier: Programming Language :: Python :: 3.7
Classifier: Programming Language :: Python :: 3.8
Classifier: License :: OSI Approved :: MIT License
Classifier: Operating System :: OS Independent
Requires-Python: >=3.6
License-File: LICENSE
Requires-Dist: pandas
Requires-Dist: matplotlib
Requires-Dist: seaborn
